[{"team_name": "Ecuador", "position": "1", "wins": "1", "draws": "0", "losses": "0", "points": "3"}, {"team_name": "Netherlands", "position": "1", "wins": "1", "draws": "0", "losses": "0", "points": "3"}, {"team_name": "Qatar", "position": "3", "wins": "0", "draws": "0", "losses": "1", "points": "0"}, {"team_name": "Senegal", "position": "3", "wins": "0", "draws": "0", "losses": "1", "points": "0"}, {"team_name": "England", "position": "1", "wins": "1", "draws": "0", "losses": "0", "points": "3"}, {"team_name": "USA", "position": "2", "wins": "0", "draws": "1", "losses": "0", "points": "1"}, {"team_name": "Wales", "position": "2", "wins": "0", "draws": "1", "losses": "0", "points": "1"}, {"team_name": "IR Iran", "position": "4", "wins": "0", "draws": "0", "losses": "1", "points": "0"}, {"team_name": "Saudi Arabia", "position": "1", "wins": "1", "draws": "0", "losses": "0", "points": "3"}, {"team_name": "Mexico", "position": "2", "wins": "0", "draws": "1", "losses": "0", "points": "1"}, {"team_name": "Poland", "position": "2", "wins": "0", "draws": "1", "losses": "0", "points": "1"}, {"team_name": "Argentina", "position": "4", "wins": "0", "draws": "0", "losses": "1", "points": "0"}, {"team_name": "Denmark", "position": "1", "wins": "0", "draws": "1", "losses": "0", "points": "1"}, {"team_name": "Tunisia", "position": "1", "wins": "0", "draws": "1", "losses": "0", "points": "1"}, {"team_name": "Australia", "position": "3", "wins": "0", "draws": "0", "losses": "0", "points": "0"}, {"team_name": "France", "position": "3", "wins": "0", "draws": "0", "losses": "0", "points": "0"}, {"team_name": "Spain", "position": "1", "wins": "0", "draws": "0", "losses": "0", "points": "0"}, {"team_name": "Costa Rica", "position": "1", "wins": "0", "draws": "0", "losses": "0", "points": "0"}, {"team_name": "Germany", "position": "1", "wins": "0", "draws": "0", "losses": "0", "points": "0"}, {"team_name": "Japan", "position": "1", "wins": "0", "draws": "0", "losses": "0", "points": "0"}, {"team_name": "Belgium", "position": "1", "wins": "0", "draws": "0", "losses": "0", "points": "0"}, {"team_name": "Canada", "position": "1", "wins": "0", "draws": "0", "losses": "0", "points": "0"}, {"team_name": "Morocco", "position": "1", "wins": "0", "draws": "0", "losses": "0", "points": "0"}, {"team_name": "Croatia", "position": "1", "wins": "0", "draws": "0", "losses": "0", "points": "0"}, {"team_name": "Brazil", "position": "1", "wins": "0", "draws": "0", "losses": "0", "points": "0"}, {"team_name": "Serbia", "position": "1", "wins": "0", "draws": "0", "losses": "0", "points": "0"}, {"team_name": "Switzerland", "position": "1", "wins": "0", "draws": "0", "losses": "0", "points": "0"}, {"team_name": "Cameroon", "position": "1", "wins": "0", "draws": "0", "losses": "0", "points": "0"}, {"team_name": "Portugal", "position": "1", "wins": "0", "draws": "0", "losses": "0", "points": "0"}, {"team_name": "Ghana", "position": "1", "wins": "0", "draws": "0", "losses": "0", "points": "0"}, {"team_name": "Uruguay", "position": "1", "wins": "0", "draws": "0", "losses": "0", "points": "0"}, {"team_name": "Korea Republic", "position": "1", "wins": "0", "draws": "0", "losses": "0", "points": "0"}]